<?xml version="1.0" encoding="UTF-8"?>
<translations isolang="sq" isolocale="" version="1.0">
<string key="Accent color">Ngjyra Accent</string>
<string key="Add a new window">Shto një dritare të re</string>
<string key="Add a note to a verse">Shto një shënim në një ajet</string>
<string key="Add a note">Shto një shënim</string>
<string key="Added notes">Shënime Added</string>
<string key="All words (maximum 3 words)">Të gjitha fjalët (maksimum 3 fjalë)</string>
<string key="An error occurred trying to connect to the network. Try again later.">Pati një gabim duke u përpjekur për t'u lidhur me rrjetin. Provoni përsëri më vonë.</string>
<string key="Are you sure?">A jeni i sigurt?</string>
<string key="Bible">Bibël</string>
<string key="Black and white dark">Bardh e zi të errët</string>
<string key="Black and white light">Dritë e zezë dhe e bardhë</string>
<string key="Blue">Blu</string>
<string key="Bookmark this verse">Bookmark këtë ajet</string>
<string key="Bookmarks">Bookmarks</string>
<string key="Border color">Ngjyra Kufitare</string>
<string key="Cancel">Anuloj</string>
<string key="Case insensitive">Rasti i pandjeshëm</string>
<string key="Clear history">Historia e qartë</string>
<string key="Columns narrower">Columns ngushta</string>
<string key="Columns wider">Columns më të gjera</string>
<string key="Commentaries">Komente</string>
<string key="Copy the last selected verses">Kopjo vargjet e fundit të zgjedhura</string>
<string key="Custom bible download addresses">Shkarko adresat Custom bible</string>
<string key="Daily plan">Plani Daily</string>
<string key="Dark but easy">Errët por e lehtë</string>
<string key="Day">Ditë</string>
<string key="Days">Ditët</string>
<string key="Default system language">Gjuha e sistemit albumit</string>
<string key="Delete?">Fshij?</string>
<string key="Download bible list">Shkarko listën biblike</string>
<string key="Download bible">Shkarko Bibla</string>
<string key="Download type">Download lloj</string>
<string key="Easy on the eyes">Lehtë në sy</string>
<string key="Exact match">Ndeshje e saktë</string>
<string key="Factory reset themes">Themes Fabrika rivendosur</string>
<string key="Font">Burim</string>
<string key="Found">Found</string>
<string key="Frame color">Frame ngjyra</string>
<string key="From the beginning to the end">Nga fillimi në fund</string>
<string key="Greek dictionary internet link">Fjalor greqisht Lidhje interneti</string>
<string key="Green">E gjelbër</string>
<string key="Hebrew dictionary internet link">Hebraisht fjalor Lidhje interneti</string>
<string key="Help">Ndihmë</string>
<string key="Highlight text markings">Highlight shenja tekst</string>
<string key="History">Histori</string>
<string key="Listen to this chapter">Dëgjoni këtë kapitull</string>
<string key="Main background color">Ngjyra kryesore sfond</string>
<string key="Main font color">Font Ngjyra kryesore</string>
<string key="Make the text size larger">Bëni madhësia e tekstit më të madhe</string>
<string key="Make the text size smaller">Bëni madhësi teksti të vogël</string>
<string key="Make this window larger">Bëni këtë dritare më të mëdha</string>
<string key="Make this window smaller">Bëni këtë dritare më të vogla</string>
<string key="Minutes/Day">Procesverbali / Dita</string>
<string key="Morphology-Abbreviated form">Forma e shkurtuar</string>
<string key="Morphology-Accusative">Akuzues</string>
<string key="Morphology-Active">Aktiv</string>
<string key="Morphology-Adjective">Mbiemër</string>
<string key="Morphology-Adverb or adverb and particle combined">Ndajfolje ose ndajfolje dhe grimcë e kombinuar</string>
<string key="Morphology-Aeolic">Aeolic</string>
<string key="Morphology-Aorist">Aorist</string>
<string key="Morphology-Apocopated form">Formulari Apocopated</string>
<string key="Morphology-Aramaic transliterated word (indeclinable)">Fjala Aramaikisht transliteruar (pashmangshëm)</string>
<string key="Morphology-Attic Greek form">Formulari Attic grek</string>
<string key="Morphology-Attic">Papafingo</string>
<string key="Morphology-Comparative">Krahasues</string>
<string key="Morphology-Conditional particle or conjunction">Grimcë e kushtëzuar apo lidhje</string>
<string key="Morphology-Conjunction or conjunctive particle">Lidhje apo grimcë lidhës</string>
<string key="Morphology-Contracted form">Formulari i kontraktuar</string>
<string key="Morphology-Contracted form, or two words merged by crasis">Forma e kontraktuar, ose dy fjalë të shkrira nga crasis</string>
<string key="Morphology-Correlative or interrogative pronoun">Përemri reciprokisht ose pyetëse</string>
<string key="Morphology-Correlative pronoun">Përemri reciprokisht</string>
<string key="Morphology-Dative">Dhanore</string>
<string key="Morphology-Definite article">Artikull të caktuar</string>
<string key="Morphology-Demonstrative pronoun">Përemri dëftor</string>
<string key="Morphology-Either middle or passive">Ose mesme ose pasiv</string>
<string key="Morphology-Feminine">Femëror</string>
<string key="Morphology-First person">Personi i parë</string>
<string key="Morphology-Future">E ardhme</string>
<string key="Morphology-Genitive">Gjinore</string>
<string key="Morphology-Hebrew transliterated word (indeclinable)">Fjala Hebraisht transliteruar (pashmangshëm)</string>
<string key="Morphology-Imperative">I domosdoshëm</string>
<string key="Morphology-Imperative-sense participle">Imperativi-kuptim pjesore</string>
<string key="Morphology-Imperfect">E pakryer</string>
<string key="Morphology-Impersonal active">Papërcaktuar aktive</string>
<string key="Morphology-Indeclinable Letter (Noun)">Letër pakalueshëm (Noun)</string>
<string key="Morphology-Indeclinable Noun of Other type">Noun pashmangshëm i llojit të tjera</string>
<string key="Morphology-Indeclinable Numeral (Adjective)">Pashmangshëm numëror (Adjective)</string>
<string key="Morphology-Indeclinable Proper Noun">Pashmangshëm duhur Noun</string>
<string key="Morphology-Indefinite pronoun">Përemri Pacaktuar</string>
<string key="Morphology-Indicative">Tregues</string>
<string key="Morphology-Infinitive">Infinitivi</string>
<string key="Morphology-Interjection">Pasthirrmë</string>
<string key="Morphology-Interrogative pronoun">Përemër pyetës</string>
<string key="Morphology-Interrogative">Pyetës</string>
<string key="Morphology-Irregular or Impure form">Formë të parregullt ose të papastër</string>
<string key="Morphology-Masculine">Mashkullor</string>
<string key="Morphology-Middle Deponent">Dëshmitar Mesme</string>
<string key="Morphology-Middle or passive deponent">Dëshmitar Mesme ose pasiv</string>
<string key="Morphology-Middle significance">Rëndësia e Mesme</string>
<string key="Morphology-Middle">Mes</string>
<string key="Morphology-Negative">Negativ</string>
<string key="Morphology-Neuter">I paanshëm</string>
<string key="Morphology-No tense stated (adverbial imperative)">Nuk ka tensionuar deklaruar (e domosdoshme ndajfoljor)</string>
<string key="Morphology-No voice stated">Nuk ka zë deklaroi</string>
<string key="Morphology-Nominative">Nominativ</string>
<string key="Morphology-Noun">Emër</string>
<string key="Morphology-Optative">Mënyrë dëshirore</string>
<string key="Morphology-Participle">Pjesore</string>
<string key="Morphology-Particle attached (with relative pronoun)">Particle bashkangjitur (me përemër relative)</string>
<string key="Morphology-Particle, disjunctive particle">Particle, grimcë disjunctive</string>
<string key="Morphology-Passive deponent">Dëshmitar pasiv</string>
<string key="Morphology-Passive">Pasiv</string>
<string key="Morphology-Perfect">I përkryer</string>
<string key="Morphology-Personal pronoun">Përemri vetor</string>
<string key="Morphology-Pluperfect">E kryer e plotë</string>
<string key="Morphology-Plural">Shumës</string>
<string key="Morphology-Possessive pronoun">Përemri pronor</string>
<string key="Morphology-Preposition">Parafjalë</string>
<string key="Morphology-Present">I pranishëm</string>
<string key="Morphology-Reciprocal pronoun">Përemri reciprok</string>
<string key="Morphology-Reflexive pronoun">Përemri refleksiv</string>
<string key="Morphology-Relative pronoun">Përemri relative</string>
<string key="Morphology-Second Aorist">Dytë Aorist</string>
<string key="Morphology-Second Future">Future dytë</string>
<string key="Morphology-Second perfect">Përsosur dytë</string>
<string key="Morphology-Second person">Fytyrë e dytë</string>
<string key="Morphology-Second pluperfect">E kryer e plotë dytë</string>
<string key="Morphology-Singular">Njëjës</string>
<string key="Morphology-Subjunctive">Lidhore</string>
<string key="Morphology-Superlative">Kulm</string>
<string key="Morphology-Third person">Vetë e tretë</string>
<string key="Morphology-Transitive">Kalimtar</string>
<string key="Morphology-Verb">Folje</string>
<string key="Morphology-Vocative">Thirrore</string>
<string key="Move this window to the left">Leviz këtë dritare në të majtë</string>
<string key="Move this window to the right">Leviz këtë dritare në të djathtë</string>
<string key="Name">Emër</string>
<string key="Notes">Shënime</string>
<string key="Nothing found">Asgjë për të gjetur</string>
<string key="One or more words">Një ose më shumë fjalë</string>
<string key="Pink">Rozë</string>
<string key="Red">I kuq</string>
<string key="Save as new theme">Ruaj si një temë të re</string>
<string key="Search conditions">Kushtet Kërko</string>
<string key="Search where">Kërkim ku</string>
<string key="Search">Kërkim</string>
<string key="Select a book to view">Zgjidh një libër për të parë</string>
<string key="Select a bookmark to delete">Zgjidh një kujtesore për të fshirë</string>
<string key="Select a chapter to view">Zgjidh një kapitull për të parë</string>
<string key="Select a theme">Zgjidh një temë</string>
<string key="Select a verse to view">Zgjidhni një varg për të parë</string>
<string key="Select bible to delete">Zgjidhni Biblën për të fshirë</string>
<string key="Select the bible">Zgjidhni biblik</string>
<string key="Select the daily plan start date">Zgjidhni planin përditshme datën e fillimit</string>
<string key="Select the daily plan">Zgjidhni planin ditor</string>
<string key="Select the language">Zgjidhni gjuhën</string>
<string key="Select the server">Zgjidhni server</string>
<string key="Select the window type">Zgjidhni llojin dritare</string>
<string key="Select what you want to hear">Zgjidhni atë që ju doni të dëgjoni</string>
<string key="Settings">Cilësimet</string>
<string key="Share the last selected verses">Share vargjet e fundit të zgjedhura</string>
<string key="Show added notes by chapter">Trego shtuar shënime nga kapitulli</string>
<string key="Show note positions">Pozicione Trego shënim</string>
<string key="Show the book name on each verse">Trego emrin libër në çdo ajet</string>
<string key="Show the chapter number on each verse">Tregoni numrin e kapitullit, në çdo varg</string>
<string key="Show the headings">Trego titujt</string>
<string key="Show the verse number on each verse">Shfaq numrin vargun për secilin varg</string>
<string key="Show the words of Jesus in red">Trego fjalët e Jezusit në të kuqe</string>
<string key="Show word morphology">Trego fjalë morfologjia</string>
<string key="Show">Shfaqje</string>
<string key="Start each verse on a new line">Filloni çdo varg në një linjë të re</string>
<string key="Talking bible internet link">Duke folur lidhjen biblike në internet</string>
<string key="Text size">Text size</string>
<string key="The New Testement">Testement New</string>
<string key="The New Testement, Psalms, Proverbs">Testement re, Psalmet, Fjalët e Urta</string>
<string key="The Old Testement">Testement Vjetër</string>
<string key="The Old and New Testement each day">New Testement çdo ditë e Vjetër dhe</string>
<string key="The bible by random chapters">Bibla sipas kapitujve të rastit</string>
<string key="The bible by topic">Bibla nga tema</string>
<string key="Theme Copy">Theme Copy</string>
<string key="Theme Paste">Paste Theme</string>
<string key="Themes">Temat</string>
<string key="Title background color">Ngjyra e sfondit Titulli</string>
<string key="Title font color">Titulli font ngjyra</string>
<string key="Too many found. Search stopped">Shumë gjetur. Kërko ndalur</string>
<string key="Translate to the current language">Translate në gjuhën e tanishme</string>
<string key="Translation">Përkthim</string>
<string key="Use internet dictionaries">Përdor fjalorë të internetit</string>
<string key="Use small verse numbers">Përdorin numrat vogla Ajeti</string>
<string key="Warm">I ngrohtë</string>
<string key="Whole bible">Bible Whole</string>
<string key="Yes">Po</string>
<string key="You must first select a verse">Ju duhet së pari të zgjidhni një varg</string>
<string key="You must have at least one bible">Ju duhet të keni të paktën një Biblën</string>
<string key="Select the daily plan current date">Zgjidhni datën e planit të përditshme tanishme</string>
<string key="Today">Sot</string>
<string key="Privacy policy">Rreth të dhënave vetjake</string>
<string key="Books">Libra</string>
<string key="Fast search">Kërkim i shpejtë</string>
<string key="Slow search">Kërko Slow</string>
<string key="The first time you do a fast search it takes a long time. Afterwards searching is very quick. Do you want to continue?">Hera e parë që ju të bëni një kërkim të shpejtë kjo merr një kohë të gjatë. Më pas në kërkim është shumë i shpejtë. A doni të vazhdoni?</string>
<string key="The bible, chronological">Bibla në mënyrë kronologjike</string>
<string key="The New Testement, chronological">Testement re në mënyrë kronologjike</string>
<string key="Invalid key. Try again">Kyç të pavlefshme. Provoni përsëri</string>
<string key="Enter key">Enter</string>
<string key="Save">Ruaj</string>
<string key="Unsuccessful import">Import pasuksesshme</string>
<string key="Successful import">Import të suksesshme</string>
<string key="Highlight name">Highlight emrin</string>
<string key="Use highlighting">Përdorimi theksim</string>
<string key="Use remote storage">Përdorimi ruajtjen e largët</string>
<string key="Copy bookmarks, highlights and notes to the clipboard">Bookmarks Copy, nxjerr në pah dhe shënimet në clipboard</string>
<string key="Import bookmarks, highlights and notes from the clipboard">Bookmarks importit, nxjerr në pah dhe shënime nga clipboard</string>
<string key="Highlight">Theksoj</string>
<string key="Synchronize to every verse">Synchronize të secilës strofë</string>
</translations>
