<?xml version="1.0" encoding="UTF-8"?>
<translations isolang="ro" isolocale="" version="1.0">
<string key="Accent color">Accent culoare</string>
<string key="Add a new window">Adauga o fereastră nouă</string>
<string key="Add a note to a verse">Adăuga o notă la un verset</string>
<string key="Add a note">Adăuga o notă</string>
<string key="Added notes">Note adăugate</string>
<string key="All words (maximum 3 words)">Toate cuvintele (maxim 3 cuvinte)</string>
<string key="An error occurred trying to connect to the network. Try again later.">A apărut o eroare încearcă să se conecteze la rețea. Încercați din nou mai târziu.</string>
<string key="Are you sure?">Ești sigur?</string>
<string key="Bible">Biblie</string>
<string key="Black and white dark">Întuneric negru și alb</string>
<string key="Black and white light">Lumina alb-negru</string>
<string key="Blue">Albastru</string>
<string key="Bookmark this verse">Bookmark acest verset</string>
<string key="Bookmarks">Semne de carte</string>
<string key="Border color">Culoare de frontieră</string>
<string key="Cancel">Anula</string>
<string key="Case insensitive">Caz insensibil</string>
<string key="Clear history">Istorie clar</string>
<string key="Columns narrower">Coloane înguste</string>
<string key="Columns wider">Coloane mai largi</string>
<string key="Commentaries">Comentarii</string>
<string key="Copy the last selected verses">Copiați în ultimele versete selectate</string>
<string key="Custom bible download addresses">Adrese de descărcare personalizat biblice</string>
<string key="Daily plan">Planul de zi cu zi</string>
<string key="Dark but easy">Întuneric, dar ușor</string>
<string key="Day">Zi</string>
<string key="Days">Zi</string>
<string key="Default system language">Limba implicită a sistemului</string>
<string key="Delete?">Ștergeți?</string>
<string key="Download bible list">Descarcă lista Biblia</string>
<string key="Download bible">Descarca Biblia</string>
<string key="Download type">Descărcați tip</string>
<string key="Easy on the eyes">Ușor de pe ochi</string>
<string key="Exact match">Potrivire exactă</string>
<string key="Factory reset themes">Teme de resetare fabrică</string>
<string key="Font">Font</string>
<string key="Found">S-au găsit</string>
<string key="Frame color">Cadru de culoare</string>
<string key="From the beginning to the end">De la început până la sfârșit</string>
<string key="Greek dictionary internet link">Dicționar greacă legătură internet</string>
<string key="Green">Verde</string>
<string key="Hebrew dictionary internet link">Legătură internet ebraică dicționar</string>
<string key="Help">Ajutor</string>
<string key="Highlight text markings">Evidențiați marcajele de text</string>
<string key="History">Istorie</string>
<string key="Listen to this chapter">Asculta la acest capitol</string>
<string key="Main background color">Culoarea de fundal principal</string>
<string key="Main font color">Culoarea fontului principal</string>
<string key="Make the text size larger">Face dimensiunea textului mai mari</string>
<string key="Make the text size smaller">Face dimensiunea textului mai mici</string>
<string key="Make this window larger">Face această fereastră mai mare</string>
<string key="Make this window smaller">Face această fereastră mică</string>
<string key="Minutes/Day">Minute / zi</string>
<string key="Morphology-Abbreviated form">Formă prescurtată</string>
<string key="Morphology-Accusative">Acuzativ</string>
<string key="Morphology-Active">Activ</string>
<string key="Morphology-Adjective">Adjectiv</string>
<string key="Morphology-Adverb or adverb and particle combined">Adverb sau adverb și particule combinate</string>
<string key="Morphology-Aeolic">Aeolic</string>
<string key="Morphology-Aorist">Aorist</string>
<string key="Morphology-Apocopated form">Formă Apocopated</string>
<string key="Morphology-Aramaic transliterated word (indeclinable)">Cuvântul aramaic tradus (indeclinabil)</string>
<string key="Morphology-Attic Greek form">Formă grec pod</string>
<string key="Morphology-Attic">Mansardă</string>
<string key="Morphology-Comparative">Comparativ</string>
<string key="Morphology-Conditional particle or conjunction">Particulă condiționată sau împreună</string>
<string key="Morphology-Conjunction or conjunctive particle">Conjuncție sau particule conjunctiv</string>
<string key="Morphology-Contracted form">Formă contractat</string>
<string key="Morphology-Contracted form, or two words merged by crasis">Formă contractată, sau două cuvinte îmbinate cu crasă</string>
<string key="Morphology-Correlative or interrogative pronoun">Pronume corelativ sau interogativ</string>
<string key="Morphology-Correlative pronoun">Pronume corelativ</string>
<string key="Morphology-Dative">Dativ</string>
<string key="Morphology-Definite article">Articol Definite</string>
<string key="Morphology-Demonstrative pronoun">Pronume demonstrativ</string>
<string key="Morphology-Either middle or passive">Ori de mijloc sau pasiv</string>
<string key="Morphology-Feminine">Feminin</string>
<string key="Morphology-First person">Prima persoană</string>
<string key="Morphology-Future">Viitor</string>
<string key="Morphology-Genitive">Genitiv</string>
<string key="Morphology-Hebrew transliterated word (indeclinable)">Cuvântul evreiesc tradus (indeclinabil)</string>
<string key="Morphology-Imperative">Imperativ</string>
<string key="Morphology-Imperative-sense participle">Imperativ-simț participiu</string>
<string key="Morphology-Imperfect">Imperfect</string>
<string key="Morphology-Impersonal active">Impersonal activ</string>
<string key="Morphology-Indeclinable Letter (Noun)">Scrisoare indeclinabil (Noun)</string>
<string key="Morphology-Indeclinable Noun of Other type">Noun indeclinabil de Alt tip</string>
<string key="Morphology-Indeclinable Numeral (Adjective)">Indeclinabil Numeral (Adjective)</string>
<string key="Morphology-Indeclinable Proper Noun">Indeclinabil Proper Noun</string>
<string key="Morphology-Indefinite pronoun">Pronume nedeterminată</string>
<string key="Morphology-Indicative">Indicativ</string>
<string key="Morphology-Infinitive">Infinitiv</string>
<string key="Morphology-Interjection">Interjecție</string>
<string key="Morphology-Interrogative pronoun">Pronume interogativ</string>
<string key="Morphology-Interrogative">Interogativ</string>
<string key="Morphology-Irregular or Impure form">Formă neregulată sau impur</string>
<string key="Morphology-Masculine">Masculin</string>
<string key="Morphology-Middle Deponent">Deponent de mijloc</string>
<string key="Morphology-Middle or passive deponent">Deponent de mijloc sau pasiv</string>
<string key="Morphology-Middle significance">Semnificație de mijloc</string>
<string key="Morphology-Middle">De mijloc</string>
<string key="Morphology-Negative">Negativ</string>
<string key="Morphology-Neuter">Neutru</string>
<string key="Morphology-No tense stated (adverbial imperative)">Nu tensionată a declarat (adverbial imperativ)</string>
<string key="Morphology-No voice stated">Nici o voce a declarat</string>
<string key="Morphology-Nominative">Nominative</string>
<string key="Morphology-Noun">Substantiv</string>
<string key="Morphology-Optative">Optativ</string>
<string key="Morphology-Participle">Participiu</string>
<string key="Morphology-Particle attached (with relative pronoun)">Particule atașat (cu pronume relativ)</string>
<string key="Morphology-Particle, disjunctive particle">Particulă, particula disjunctiv</string>
<string key="Morphology-Passive deponent">Deponent pasiv</string>
<string key="Morphology-Passive">Pasiv</string>
<string key="Morphology-Perfect">Perfect</string>
<string key="Morphology-Personal pronoun">Pronume personal</string>
<string key="Morphology-Pluperfect">Mai mult ca perfect</string>
<string key="Morphology-Plural">Plural</string>
<string key="Morphology-Possessive pronoun">Pronume posesiv</string>
<string key="Morphology-Preposition">Prepoziție</string>
<string key="Morphology-Present">Prezent</string>
<string key="Morphology-Reciprocal pronoun">Pronume reciproc</string>
<string key="Morphology-Reflexive pronoun">Pronume reflexiv</string>
<string key="Morphology-Relative pronoun">Pronume relativ</string>
<string key="Morphology-Second Aorist">În al doilea rând AORIST</string>
<string key="Morphology-Second Future">În al doilea rând viitor</string>
<string key="Morphology-Second perfect">În al doilea rând perfectă</string>
<string key="Morphology-Second person">A doua persoană</string>
<string key="Morphology-Second pluperfect">Al doilea mai mult ca perfect</string>
<string key="Morphology-Singular">Singular</string>
<string key="Morphology-Subjunctive">Conjunctiv</string>
<string key="Morphology-Superlative">Superlativ</string>
<string key="Morphology-Third person">Persoana a treia</string>
<string key="Morphology-Transitive">Tranzitiv</string>
<string key="Morphology-Verb">Verb</string>
<string key="Morphology-Vocative">Vocativ</string>
<string key="Move this window to the left">Mutați această fereastră la stânga</string>
<string key="Move this window to the right">Mutați această fereastră la dreapta</string>
<string key="Name">Nume</string>
<string key="Notes">Notițe</string>
<string key="Nothing found">Nimic găsit</string>
<string key="One or more words">Unul sau mai multe cuvinte</string>
<string key="Pink">Roz</string>
<string key="Red">Roșu</string>
<string key="Save as new theme">Salvați ca o temă nouă</string>
<string key="Search conditions">Condiții de căutare</string>
<string key="Search where">Cauta in</string>
<string key="Search">Căutare</string>
<string key="Select a book to view">Selectați o carte pentru a vizualiza</string>
<string key="Select a bookmark to delete">Selectați un marcaj pentru a șterge</string>
<string key="Select a chapter to view">Selectați un capitol pentru a vizualiza</string>
<string key="Select a theme">Selectați o temă</string>
<string key="Select a verse to view">Selectați un verset pentru a vizualiza</string>
<string key="Select bible to delete">Selectați Biblia pentru a șterge</string>
<string key="Select the bible">Selectați Biblia</string>
<string key="Select the daily plan start date">Selectați de zi cu zi planul de data de începere</string>
<string key="Select the daily plan">Selectați planul de zi cu zi</string>
<string key="Select the language">Selectați limba</string>
<string key="Select the server">Selectați serverul</string>
<string key="Select the window type">Selectați tipul de fereastră</string>
<string key="Select what you want to hear">Selectați ceea ce vrei sa auzi</string>
<string key="Settings">Setări</string>
<string key="Share the last selected verses">Împărtăși ultimele versete selectate</string>
<string key="Show added notes by chapter">Arată adăugat note de capitol</string>
<string key="Show note positions">Poziții spectacol note</string>
<string key="Show the book name on each verse">Arata numele de carte de la fiecare verset</string>
<string key="Show the chapter number on each verse">Arată numărul capitolului pe fiecare verset</string>
<string key="Show the headings">Arată titlurile</string>
<string key="Show the verse number on each verse">Arată numărul verset la fiecare verset</string>
<string key="Show the words of Jesus in red">Arată cuvintele lui Isus în roșu</string>
<string key="Show word morphology">Morfologie spectacol cuvânt</string>
<string key="Show">Spectacol</string>
<string key="Start each verse on a new line">Începeți fiecare verset pe o linie nouă</string>
<string key="Talking bible internet link">Vorbind legătură internet Biblie</string>
<string key="Text size">Dimensiunea textului</string>
<string key="The New Testement">Noul Testement</string>
<string key="The New Testement, Psalms, Proverbs">New Testement, Psalmi, Proverbe</string>
<string key="The Old Testement">Vechiul Testement</string>
<string key="The Old and New Testement each day">Vechiul și Noul Testement în fiecare zi</string>
<string key="The bible by random chapters">Biblia pe capitole aleatoare</string>
<string key="The bible by topic">Biblia de subiect</string>
<string key="Theme Copy">Tema Copy</string>
<string key="Theme Paste">Tema Paste</string>
<string key="Themes">Tematică</string>
<string key="Title background color">Culoarea de fundal titlu</string>
<string key="Title font color">Culoarea fontului titlu</string>
<string key="Too many found. Search stopped">Prea multe găsit. Căutare oprit</string>
<string key="Translate to the current language">Traduce în limba curentă</string>
<string key="Translation">Traducere</string>
<string key="Use internet dictionaries">Utilizați dicționare internet</string>
<string key="Use small verse numbers">Utilizați numere verset mici</string>
<string key="Warm">Cald</string>
<string key="Whole bible">Total biblia</string>
<string key="Yes">Da</string>
<string key="You must first select a verse">Trebuie să selectați mai întâi un vers</string>
<string key="You must have at least one bible">Trebuie să aveți cel puțin o Biblie</string>
<string key="Select the daily plan current date">Selectați data de actualul plan de zi cu zi</string>
<string key="Today">Azi</string>
<string key="Privacy policy">Politica de confidențialitate</string>
<string key="Books">Cărți</string>
<string key="Fast search">Căutare rapidă</string>
<string key="Slow search">Căutare lent</string>
<string key="The first time you do a fast search it takes a long time. Afterwards searching is very quick. Do you want to continue?">Prima dată când faci o căutare rapidă este nevoie de o perioadă lungă de timp. Căutarea după aceea este foarte rapid. Vrei să continui?</string>
<string key="The bible, chronological">Biblia în ordine cronologică</string>
<string key="The New Testement, chronological">New Testement în ordine cronologică</string>
<string key="Invalid key. Try again">Cheie invalid. Încercați din nou</string>
<string key="Enter key">Tasta Enter</string>
<string key="Save">Salva</string>
<string key="Unsuccessful import">Import succes</string>
<string key="Successful import">Import de succes</string>
<string key="Highlight name">Evidențiați nume</string>
<string key="Use highlighting">Utilizați evidențierea</string>
<string key="Use remote storage">Utilizați de stocare la distanță</string>
<string key="Copy bookmarks, highlights and notes to the clipboard">Marcajele de copiere, scoate în evidență și note la clipboard</string>
<string key="Import bookmarks, highlights and notes from the clipboard">Marcajele de import, scoate în evidență și note din clipboard</string>
<string key="Highlight">Evidențiați</string>
<string key="Synchronize to every verse">Sincroniza la fiecare verset</string>
<string key="OneDrive backup / restore">OneDrive backup / restore</string>
<string key="Select the items you want to backup / restore. Then hit the button at the bottom">Selectați elementele pe care doriți să backup / restore. Apoi apăsați pe butonul din partea de jos</string>
<string key="Backup">Backup</string>
<string key="Restore">Restabili</string>
<string key="Bookmarks and custom notes">Marcaje și note personalizate</string>
<string key="Window setup">Configurare fereastră</string>
<string key="Folder on OneDrive">Folder de pe OneDrive</string>
<string key="Doesn't exist in OneDrive. Remove it and try again">Nu există în OneDrive. Scoateți-l și încercați din nou</string>
<string key="There is no backup to restore">Nu există nici o rezervă pentru a restaura</string>
<string key="Connect to OneDrive">Conectați-vă la OneDrive</string>
</translations>
