<?xml version="1.0" encoding="UTF-8"?>
<translations isolang="sq" isolocale="" version="1.0">
<string key="Add new window">Shto dritare të re</string>
<string key="Add to bookmarks">Add to bookmarks</string>
<string key="All words (maximum 3 words)">Të gjitha fjalët (maksimum 3 fjalë)</string>
<string key="An error occured. Do you want to completely erase the memory for this program?">Ka ndodhur një gabim. A doni të fshihet tërësisht e kujtesës për këtë program?</string>
<string key="Bible">Bibël</string>
<string key="Bookmarks">Bookmarks</string>
<string key="Cancel">Anuloj</string>
<string key="Case insensitive">Rasti i pandjeshëm</string>
<string key="Clear history">Pastro historinë</string>
<string key="Delete?">Delete?</string>
<string key="Download bible list">Lista Download bible</string>
<string key="Download bible">Bibla Download</string>
<string key="Download bibles">Shkarko Bibles</string>
<string key="Exact match">ndeshje e saktë</string>
<string key="Found">Found</string>
<string key="Help">Ndihmë</string>
<string key="History">Histori</string>
<string key="New Testement">Ri Testement</string>
<string key="Notes">Shënime</string>
<string key="Nothing found">Asgjë për të gjetur</string>
<string key="Old Testement">Vjetër Testement</string>
<string key="One or more words">Një ose më shumë fjalë</string>
<string key="Save">Ruaj</string>
<string key="Search conditions">Kushtet e kërkimit</string>
<string key="Search where">Search ku</string>
<string key="Search">Kërko</string>
<string key="Select bible to delete">Zgjidh të fshini Bibla</string>
<string key="Select book and chapter">Zgjidhni librin dhe kapitullin</string>
<string key="Select book">Libri Zgjidh</string>
<string key="Select bookmark to delete">bookmark Zgjidh për të fshirë</string>
<string key="Select chapter">kapitull Zgjidh</string>
<string key="Select the bible">Zgjidhni Bibla</string>
<string key="Select the language">Zgjidhni gjuhën</string>
<string key="Select the server">Zgjidhni server</string>
<string key="Select the window type">Zgjidhni llojin e dritares</string>
<string key="Settings">Paneli i punëve</string>
<string key="Text size">Madhësia Tekst</string>
<string key="Too many found. Search stopped">Shumë gjetur. Search ndal</string>
<string key="Whole bible">Bibla gjithë</string>
<string key="You must have at least one bible">Ju duhet të keni të paktën një bible</string>
<string key="An error occurred trying to connect to the network. Try again later.">Një gabim ndodhi duke u përpjekur për t'u lidhur me rrjetin. Provoni përsëri më vonë.</string>
</translations>
