<translations isolang="fa" isolocale="" version="1.0">
<string key="Add a note">اضافه کردن یک یادداشت</string>
<string key="Add new window">اضافه کردن پنجره جدید</string>
<string key="Add to bookmarks">اضافه کردن به بوک مارک ها</string>
<string key="Added notes">اضافه شده در یادداشت ها</string>
<string key="All words (maximum 3 words)">همه واژه ها (حداکثر 3 کلمه)</string>
<string key="An error occurred trying to connect to the network. Try again later.">یک خطا رخ داده در تلاش برای اتصال به شبکه می باشد. دوباره تلاش کنید.</string>
<string key="Bible">کتاب مقدس</string>
<string key="Bookmarks">ثبت نام</string>
<string key="Case insensitive">مورد حساس</string>
<string key="Clear history">پاک کردن تاریخچه</string>
<string key="Custom bible download addresses">سفارشی کتاب مقدس دانلود آدرس</string>
<string key="Daily plan">برنامه روزانه</string>
<string key="Day">روز</string>
<string key="Days">روز</string>
<string key="Default settings">تنظیمات پیش فرض</string>
<string key="Default system language">زبان پیش فرض سیستم</string>
<string key="Delete?">حذف؟</string>
<string key="Download bible list">دانلود لیست کتاب مقدس</string>
<string key="Download bible">دانلود کتاب مقدس</string>
<string key="Download bibles">bibles دانلود</string>
<string key="Exact match">جواب دقیق</string>
<string key="Found">پیدا نشد</string>
<string key="From the beginning to the end">از آغاز تا پایان</string>
<string key="Greek dictionary internet link">فرهنگ لغت یونانی لینک اینترنت</string>
<string key="Hebrew dictionary internet link">فرهنگ لغت عبری لینک اینترنت</string>
<string key="Help">کمک</string>
<string key="Highlight text markings">نماد نشانه گذاری متن</string>
<string key="History">تاریخ</string>
<string key="Minutes/Day">دقیقه در روز</string>
<string key="Morphology-Abbreviated form">خلاصه</string>
<string key="Morphology-Accusative">رایی</string>
<string key="Morphology-Active">فعال</string>
<string key="Morphology-Adjective">صفت</string>
<string key="Morphology-Adverb or adverb and particle combined">قید و یا قید و ذرات ترکیبی</string>
<string key="Morphology-Aeolic">Aeolic</string>
<string key="Morphology-Aorist">Aorist</string>
<string key="Morphology-Apocopated form">فرم Apocopated</string>
<string key="Morphology-Aramaic transliterated word (indeclinable)">ترجمه کلمه به زبان آرامی (غیر قابل تصریف)</string>
<string key="Morphology-Attic Greek form">اتاق زیر شیروانی شکل یونانی</string>
<string key="Morphology-Attic">اطاق کوچک زیر شیروانی</string>
<string key="Morphology-Comparative">تطبیقی</string>
<string key="Morphology-Conditional particle or conjunction">ذرات مشروط و یا همراه</string>
<string key="Morphology-Conjunction or conjunctive particle">همراه و یا ذره حرف ربط</string>
<string key="Morphology-Contracted form">فرم قرارداد</string>
<string key="Morphology-Contracted form, or two words merged by crasis">فرم قراردادی ، یا دو کلمه با هم ادغام شدند توسط crasis</string>
<string key="Morphology-Correlative or interrogative pronoun">همبستگی و یا ضمیر پرسشی</string>
<string key="Morphology-Correlative pronoun">ضمیر همبستگی</string>
<string key="Morphology-Dative">حالت مفعولی</string>
<string key="Morphology-Definite article">مقاله قطعی</string>
<string key="Morphology-Demonstrative pronoun">ضمیر اشاره</string>
<string key="Morphology-Either middle or passive">در هر دو متوسط ​​و یا غیر فعال</string>
<string key="Morphology-Feminine">زنان</string>
<string key="Morphology-First person">اول شخص</string>
<string key="Morphology-Future">آینده</string>
<string key="Morphology-Genitive">حالت اضافه</string>
<string key="Morphology-Hebrew transliterated word (indeclinable)">ترجمه عبری کلمه ای (غیر قابل تصریف)</string>
<string key="Morphology-Imperative">امری</string>
<string key="Morphology-Imperative-sense participle">احساس ضرورت ، وجه وصفی مجهول</string>
<string key="Morphology-Imperfect">ناقص</string>
<string key="Morphology-Impersonal active">غیر شخصی فعال</string>
<string key="Morphology-Indeclinable Letter (Noun)">نامه غیر قابل تصریف (اسم)</string>
<string key="Morphology-Indeclinable Noun of Other type">اسم غیر قابل تصریف از نوع دیگر</string>
<string key="Morphology-Indeclinable Numeral (Adjective)">بر اساس اعداد غیر قابل تصریف (انگلیسی)</string>
<string key="Morphology-Indeclinable Proper Noun">صرف نشدنی نام مناسب</string>
<string key="Morphology-Indefinite pronoun">ضمیر مدت نامعلوم</string>
<string key="Morphology-Indicative">نشان دهنده</string>
<string key="Morphology-Infinitive">مصدر</string>
<string key="Morphology-Interjection">حرف ندا</string>
<string key="Morphology-Interrogative pronoun">ضمیر پرسشی</string>
<string key="Morphology-Interrogative">ادوات استفهام</string>
<string key="Morphology-Irregular or Impure form">و یا به صورت نامنظم Impure</string>
<string key="Morphology-Masculine">مردانه</string>
<string key="Morphology-Middle Deponent">میانه Deponent</string>
<string key="Morphology-Middle or passive deponent">میانه و یا غیر فعال deponent</string>
<string key="Morphology-Middle significance">اهمیت میانه</string>
<string key="Morphology-Middle">متوسط</string>
<string key="Morphology-Negative">منفی</string>
<string key="Morphology-Neuter">خنثی</string>
<string key="Morphology-No tense stated (adverbial imperative)">بدون اعلام زمان (قیدی ضروری)</string>
<string key="Morphology-No voice stated">بدون صدا اعلام کرد</string>
<string key="Morphology-Nominative">فاعلی</string>
<string key="Morphology-Noun">اسم</string>
<string key="Morphology-Optative">وابسته به طلب و تمنا</string>
<string key="Morphology-Participle">وجه وصفی مجهول</string>
<string key="Morphology-Particle attached (with relative pronoun)">ذرات متصل شده (با ضمیر نسبی)</string>
<string key="Morphology-Particle, disjunctive particle">ذرات ، ذرات منفصل</string>
<string key="Morphology-Passive deponent">deponent غیر فعال</string>
<string key="Morphology-Passive">غیر فعال</string>
<string key="Morphology-Perfect">کامل</string>
<string key="Morphology-Personal pronoun">ضمیر شخصی</string>
<string key="Morphology-Pluperfect">فعل ماضی بعید</string>
<string key="Morphology-Plural">جمع</string>
<string key="Morphology-Possessive pronoun">ضمیر ملکی</string>
<string key="Morphology-Preposition">حرف اضافه</string>
<string key="Morphology-Present">حاضر</string>
<string key="Morphology-Reciprocal pronoun">ضمیر متقابل</string>
<string key="Morphology-Reflexive pronoun">ضمیرفاعلی</string>
<string key="Morphology-Relative pronoun">ضمیر نسبی</string>
<string key="Morphology-Second Aorist">Aorist دوم</string>
<string key="Morphology-Second Future">آینده دوم</string>
<string key="Morphology-Second perfect">دوم کامل</string>
<string key="Morphology-Second person">دوم شخص</string>
<string key="Morphology-Second pluperfect">دوم فعل ماضی بعید</string>
<string key="Morphology-Singular">مفرد</string>
<string key="Morphology-Subjunctive">وجه شرطی</string>
<string key="Morphology-Superlative">عالی</string>
<string key="Morphology-Third person">سوم شخص</string>
<string key="Morphology-Transitive">متعدی</string>
<string key="Morphology-Verb">فعل</string>
<string key="Morphology-Vocative">ایی</string>
<string key="Notes">یادداشت ها</string>
<string key="Nothing found">هیچ چیزی پیدا نشد</string>
<string key="One or more words">از یک یا کلمات</string>
<string key="Rate this program">ارزشیابی شما از این برنامه</string>
<string key="Search conditions">شرایط جستجو</string>
<string key="Search where">جستجو که در آن</string>
<string key="Search">جستجو</string>
<string key="Select bible to delete">انتخاب کتاب مقدس را حذف کنید</string>
<string key="Select book and chapter">کتاب را انتخاب کنید و فصل</string>
<string key="Select book">انتخاب کتاب</string>
<string key="Select bookmark to delete">انتخاب کنید نشانه را حذف کنید</string>
<string key="Select chapter">انتخاب کنید فصل</string>
<string key="Select day">انتخاب روز</string>
<string key="Select the bible">انتخاب کتاب مقدس</string>
<string key="Select the daily plan start date">انتخاب کنید روزانه تاریخ شروع طرح</string>
<string key="Select the daily plan">انتخاب کنید برنامه روزانه</string>
<string key="Select the language">انتخاب زبان</string>
<string key="Select the server">انتخاب سرور</string>
<string key="Select the window type">انتخاب نوع پنجره</string>
<string key="Send mail">آدرس ایمیل</string>
<string key="Send message">ارسال پیام</string>
<string key="Settings">تنظیمات</string>
<string key="Show Strong&#39;s numbers">تعداد نمایش استرانگ</string>
<string key="Show added notes by chapter">نمایش یادداشت ها اضافه شده توسط فصل</string>
<string key="Show note positions">نمایش موقعیت توجه داشته باشید</string>
<string key="Show the book name on each verse">نمایش نام کتاب در هر آیه</string>
<string key="Show the chapter number on each verse">نمایش تعداد فصل در هر آیه</string>
<string key="Show the headings">نمایش عنوان</string>
<string key="Show the verse number on each verse">نمایش تعداد آیه در هر آیه</string>
<string key="Show the words of Jesus in red">نمایش سخنان عیسی در قرمز</string>
<string key="Show word morphology">نمایش مورفولوژی کلمه</string>
<string key="Start each verse on a new line">شروع هر آیه را در یک خط جدید</string>
<string key="Text size">اندازه متن</string>
<string key="The New Testement">Testement جدید</string>
<string key="The New Testement, Psalms, Proverbs">Testement جدید ، مزامیر ، امثال</string>
<string key="The Old Testement">Testement قدیمی</string>
<string key="The Old and New Testement each day">Testement قدیم و جدید در هر روز</string>
<string key="The bible by random chapters">کتاب مقدس فصل های تصادفی</string>
<string key="The bible by topic">کتاب مقدس موضوع</string>
<string key="Too many found. Search stopped">بیش از حد بسیاری در بر داشت. جستجو را متوقف</string>
<string key="Use small verse numbers">استفاده از شماره آیه کوچک</string>
<string key="Whole bible">مجموع کتاب مقدس</string>
<string key="You must first select a verse">شما باید اول یک آیه را انتخاب کنید</string>
<string key="You must have at least one bible">شما باید حداقل یک کتاب مقدس دارند</string>
</translations>
