<?xml version="1.0" encoding="UTF-8"?>
<translations isolang="fa" isolocale="" version="1.0">
<string key="Accent color">رنگ لهجه</string>
<string key="Add a new window">اضافه کردن یک پنجره جدید</string>
<string key="Add a note to a verse">اضافه کردن یک یادداشت به یک آیه</string>
<string key="Add a note">اضافه کردن یک یادداشت</string>
<string key="Added notes">یادداشت اضافه شده</string>
<string key="All words (maximum 3 words)">همه واژگان (حداکثر 3 کلمه)</string>
<string key="An error occurred trying to connect to the network. Try again later.">تلاش برای اتصال به شبکه خطایی رخ داد. بعدا دوباره سعی کنید.</string>
<string key="Are you sure?">آیا مطمئن هستید؟</string>
<string key="Bible">کتاب مقدس</string>
<string key="Black and white dark">سیاه و سفید تیره</string>
<string key="Black and white light">سیاه و سفید نور</string>
<string key="Blue">ابی</string>
<string key="Bookmark this verse">این آیه</string>
<string key="Bookmarks">بوک مارک ها</string>
<string key="Border color">رنگ حاشیه</string>
<string key="Cancel">لغو کردن</string>
<string key="Case insensitive">حروف حساس</string>
<string key="Clear history">پاک کردن تاریخچه</string>
<string key="Columns narrower">ستون باریک تر</string>
<string key="Columns wider">ستون های گسترده تر</string>
<string key="Commentaries">تفسیر</string>
<string key="Copy the last selected verses">کپی آیات گذشته انتخاب شده</string>
<string key="Custom bible download addresses">آدرس دانلود کتاب مقدس سفارشی</string>
<string key="Daily plan">برنامه روزانه</string>
<string key="Dark but easy">تاریک اما آسان</string>
<string key="Day">روز</string>
<string key="Days">روز</string>
<string key="Default system language">زبان پیش فرض سیستم</string>
<string key="Delete?">حذف شود؟</string>
<string key="Download bible list">دانلود فهرست کتاب مقدس</string>
<string key="Download bible">دانلود کتاب مقدس</string>
<string key="Download type">دانلود نوع</string>
<string key="Easy on the eyes">آسان بر روی چشم</string>
<string key="Exact match">جواب دقیق</string>
<string key="Factory reset themes">تم های تنظیم مجدد کارخانه</string>
<string key="Font">فونت</string>
<string key="Found">یافت</string>
<string key="Frame color">رنگ قاب</string>
<string key="From the beginning to the end">از آغاز تا پایان</string>
<string key="Greek dictionary internet link">فرهنگ لغت یونانی لینک اینترنت</string>
<string key="Green">سبز</string>
<string key="Hebrew dictionary internet link">لینک اینترنتی عبری فرهنگ لغت</string>
<string key="Help">کمک</string>
<string key="Highlight text markings">نماد نشانه گذاری متن</string>
<string key="History">تاریخ</string>
<string key="Listen to this chapter">گوش دادن به این فصل</string>
<string key="Main background color">رنگ پس زمینه اصلی</string>
<string key="Main font color">رنگ فونت اصلی</string>
<string key="Make the text size larger">را اندازه متن بزرگتر</string>
<string key="Make the text size smaller">را اندازه متن کوچکتر</string>
<string key="Make this window larger">این را در پنجره بزرگتر</string>
<string key="Make this window smaller">را این پنجره کوچکتر</string>
<string key="Minutes/Day">دقیقه / روز</string>
<string key="Morphology-Abbreviated form">فرم خلاصه شده</string>
<string key="Morphology-Accusative">رایی</string>
<string key="Morphology-Active">فعال</string>
<string key="Morphology-Adjective">صفت</string>
<string key="Morphology-Adverb or adverb and particle combined">قید یا قید و ذرات ترکیبی</string>
<string key="Morphology-Aeolic">Aeolic</string>
<string key="Morphology-Aorist">Aorist</string>
<string key="Morphology-Apocopated form">فرم Apocopated</string>
<string key="Morphology-Aramaic transliterated word (indeclinable)">کلمه به زبان آرامی ترجمه (غیر قابل تصریف)</string>
<string key="Morphology-Attic Greek form">فرم یونانی اتاق زیر شیروانی</string>
<string key="Morphology-Attic">اطاق کوچک زیر شیروانی</string>
<string key="Morphology-Comparative">مقایسه ای</string>
<string key="Morphology-Conditional particle or conjunction">ذرات شرطی یا همراه</string>
<string key="Morphology-Conjunction or conjunctive particle">ارتباط و یا ذرات ملتحمه</string>
<string key="Morphology-Contracted form">فرم قرارداد</string>
<string key="Morphology-Contracted form, or two words merged by crasis">فرم قرارداد، یا دو کلمه با هم ادغام شده توسط crasis</string>
<string key="Morphology-Correlative or interrogative pronoun">ضمیر همبستگی و یا پرسشی</string>
<string key="Morphology-Correlative pronoun">ضمیر همبستگی</string>
<string key="Morphology-Dative">حالت مفعولی</string>
<string key="Morphology-Definite article">تعریف</string>
<string key="Morphology-Demonstrative pronoun">ضمیر نمایشی</string>
<string key="Morphology-Either middle or passive">در هر دو صورت متوسط ​​یا غیر فعال</string>
<string key="Morphology-Feminine">زنان</string>
<string key="Morphology-First person">فرد نخست</string>
<string key="Morphology-Future">بعدی</string>
<string key="Morphology-Genitive">حالت اضافه</string>
<string key="Morphology-Hebrew transliterated word (indeclinable)">واژه عبری ترجمه (غیر قابل تصریف)</string>
<string key="Morphology-Imperative">امری</string>
<string key="Morphology-Imperative-sense participle">وجه وصفی ضروری حس</string>
<string key="Morphology-Imperfect">ناقص</string>
<string key="Morphology-Impersonal active">غیر شخصی فعال</string>
<string key="Morphology-Indeclinable Letter (Noun)">نامه غیر قابل تصریف (اسم)</string>
<string key="Morphology-Indeclinable Noun of Other type">اسم غیر قابل تصریف از دیگر نوع</string>
<string key="Morphology-Indeclinable Numeral (Adjective)">غیر قابل تصریف اعداد (صفت)</string>
<string key="Morphology-Indeclinable Proper Noun">غیر قابل تصریف مناسب اسم</string>
<string key="Morphology-Indefinite pronoun">ضمیر نامحدود</string>
<string key="Morphology-Indicative">نشان دهنده</string>
<string key="Morphology-Infinitive">مصدر</string>
<string key="Morphology-Interjection">حرف ندا</string>
<string key="Morphology-Interrogative pronoun">ضمیر پرسشی</string>
<string key="Morphology-Interrogative">پرسشی</string>
<string key="Morphology-Irregular or Impure form">شکل نامنظم و یا ناخالص</string>
<string key="Morphology-Masculine">مردانه</string>
<string key="Morphology-Middle Deponent">Deponent میانه</string>
<string key="Morphology-Middle or passive deponent">deponent میانه یا غیر فعال</string>
<string key="Morphology-Middle significance">اهمیت میانه</string>
<string key="Morphology-Middle">متوسط</string>
<string key="Morphology-Negative">منفی</string>
<string key="Morphology-Neuter">خنثی</string>
<string key="Morphology-No tense stated (adverbial imperative)">بدون تنش اظهار داشت (ضروری قیدی)</string>
<string key="Morphology-No voice stated">بدون صدا اعلام کرد</string>
<string key="Morphology-Nominative">فاعلی</string>
<string key="Morphology-Noun">اسم</string>
<string key="Morphology-Optative">تمنایی</string>
<string key="Morphology-Participle">وجه وصفی</string>
<string key="Morphology-Particle attached (with relative pronoun)">ذرات متصل شده (با ضمیر نسبی)</string>
<string key="Morphology-Particle, disjunctive particle">ذرات، ذرات گسسته</string>
<string key="Morphology-Passive deponent">deponent منفعل</string>
<string key="Morphology-Passive">غیر فعال</string>
<string key="Morphology-Perfect">کامل</string>
<string key="Morphology-Personal pronoun">ضمیر شخصی</string>
<string key="Morphology-Pluperfect">خیلی عالی</string>
<string key="Morphology-Plural">جمع</string>
<string key="Morphology-Possessive pronoun">ضمیر ملکی</string>
<string key="Morphology-Preposition">حرف اضافه</string>
<string key="Morphology-Present">حاضر</string>
<string key="Morphology-Reciprocal pronoun">ضمیر متقابل</string>
<string key="Morphology-Reflexive pronoun">ضمیرفاعلی</string>
<string key="Morphology-Relative pronoun">ضمیر نسبی</string>
<string key="Morphology-Second Aorist">Aorist دوم</string>
<string key="Morphology-Second Future">آینده دوم</string>
<string key="Morphology-Second perfect">کامل دوم</string>
<string key="Morphology-Second person">دوم شخص</string>
<string key="Morphology-Second pluperfect">خیلی عالی دوم</string>
<string key="Morphology-Singular">مفرد</string>
<string key="Morphology-Subjunctive">وجه شرطی</string>
<string key="Morphology-Superlative">عالی</string>
<string key="Morphology-Third person">سوم شخص</string>
<string key="Morphology-Transitive">متعدی</string>
<string key="Morphology-Verb">فعل</string>
<string key="Morphology-Vocative">ندایی</string>
<string key="Move this window to the left">انتقال این پنجره به سمت چپ</string>
<string key="Move this window to the right">حرکت این پنجره را به سمت راست</string>
<string key="Name">نام</string>
<string key="Notes">یادداشت ها</string>
<string key="Nothing found">هیچ چیزی پیدا نشد</string>
<string key="One or more words">یک یا چند کلمه</string>
<string key="Pink">رنگ صورتی</string>
<string key="Red">قرمز</string>
<string key="Save as new theme">ذخیره به عنوان یک موضوع جدید</string>
<string key="Search conditions">شرایط جستجو</string>
<string key="Search where">جست و جو که در آن</string>
<string key="Search">جستجو</string>
<string key="Select a book to view">یک کتاب انتخاب کنید برای مشاهده</string>
<string key="Select a bookmark to delete">انتخاب یک نشانه را حذف کنید</string>
<string key="Select a chapter to view">انتخاب فصل برای مشاهده</string>
<string key="Select a theme">انتخاب موضوع</string>
<string key="Select a verse to view">انتخاب یک آیه برای مشاهده</string>
<string key="Select bible to delete">انتخاب کتاب مقدس را حذف کنید</string>
<string key="Select the bible">انتخاب کتاب مقدس</string>
<string key="Select the daily plan start date">تاریخ شروع برنامه روزانه را انتخاب کنید</string>
<string key="Select the daily plan">را انتخاب کنید برنامه روزانه</string>
<string key="Select the language">انتخاب زبان</string>
<string key="Select the server">انتخاب سرور</string>
<string key="Select the window type">انتخاب نوع پنجره</string>
<string key="Select what you want to hear">انتخاب آنچه شما می خواهید برای شنیدن</string>
<string key="Settings">تنظیمات</string>
<string key="Share the last selected verses">به اشتراک گذاشتن آیات گذشته انتخاب شده</string>
<string key="Show added notes by chapter">نمایش یادداشت های فصل اضافه شده است</string>
<string key="Show note positions">مواضع نمایش توجه داشته باشید</string>
<string key="Show the book name on each verse">نمایش نام کتاب بر روی هر آیه</string>
<string key="Show the chapter number on each verse">نمایش تعداد فصل مربوط به هر آیه</string>
<string key="Show the headings">نمایش عناوین</string>
<string key="Show the verse number on each verse">نمایش تعداد آیه در هر آیه</string>
<string key="Show the words of Jesus in red">نمایش کلمات عیسی به رنگ قرمز</string>
<string key="Show word morphology">مورفولوژی نمایش کلمه</string>
<string key="Show">نمایش</string>
<string key="Start each verse on a new line">شروع هر آیه در یک خط جدید</string>
<string key="Talking bible internet link">صحبت کردن لینک اینترنتی کتاب مقدس</string>
<string key="Text size">اندازه متن</string>
<string key="The New Testement">جدید Testement</string>
<string key="The New Testement, Psalms, Proverbs">جدید Testement، مزامیر، امثال</string>
<string key="The Old Testement">قدیمی Testement</string>
<string key="The Old and New Testement each day">قدیمی و جدید Testement هر روز</string>
<string key="The bible by random chapters">کتاب مقدس توسط فصل های تصادفی</string>
<string key="The bible by topic">کتاب مقدس موضوع</string>
<string key="Theme Copy">تم کپی</string>
<string key="Theme Paste">چسباندن تم</string>
<string key="Themes">تم ها</string>
<string key="Title background color">رنگ عنوان پس زمینه</string>
<string key="Title font color">رنگ عنوان فونت</string>
<string key="Too many found. Search stopped">بیش از حد بسیاری یافت می شود. جستجو متوقف شد</string>
<string key="Translate to the current language">ترجمه به زبان جاری</string>
<string key="Translation">ترجمه</string>
<string key="Use internet dictionaries">استفاده از لغت نامه اینترنت</string>
<string key="Use small verse numbers">استفاده از اعداد کوچک آیه</string>
<string key="Warm">گرم</string>
<string key="Whole bible">کتاب مقدس مجموع</string>
<string key="Yes">بله</string>
<string key="You must first select a verse">شما ابتدا باید یک آیه را انتخاب کنید</string>
<string key="You must have at least one bible">شما باید حداقل یک کتاب مقدس دارند</string>
<string key="Select the daily plan current date">تاریخ جاری برنامه روزانه را انتخاب کنید</string>
<string key="Today">امروز</string>
<string key="Privacy policy">سیاست حفظ اسرار</string>
<string key="Books">کتاب ها</string>
<string key="Fast search">جستجو سریع</string>
<string key="Slow search">جستجو آهسته</string>
<string key="The first time you do a fast search it takes a long time. Afterwards searching is very quick. Do you want to continue?">اولین باری که انجام یک جستجوی سریع در مدت زمان طولانی طول می کشد. پس از آن در جستجوی بسیار سریع است. آیا می خواهید ادامه دهید؟</string>
<string key="The bible, chronological">کتاب مقدس به ترتیب زمانی</string>
<string key="The New Testement, chronological">Testement جدید به ترتیب زمانی</string>
<string key="Invalid key. Try again">کلید نامعتبر است. دوباره سعی کنید</string>
<string key="Enter key">کلیدی را وارد کنید</string>
<string key="Save">جویی در هزینه</string>
<string key="Fast search help text">جستجوی سریع کاهش سرعت اولین بار شما از آن استفاده در هر زمان کتاب مقدس و به سرعت پس از آن. جستجوی سریع باز می گردد آیات شامل تمام کلمات داده شده. قرار دادن یک "+" در جلوی هر کلمه برای پیدا کردن هر یک از کلمات داده شده در هر آیه. قرار دهید "-" در مقابل یک کلمه برای پیدا کردن همه از آیات که آن کلمه را ندارد. نویسه عام "*" و "؟" می تواند مورد استفاده قرار گیرد. در زبان با استفاده از کاراکتر مثل چینی و ژاپنی شما باید قبل و بعد از هر یک از شخصیت را "*". استفاده از تنها جستجوی آهسته برای پیدا کردن "strongs در" اعداد.</string>
<string key="Unsuccessful import">واردات ناموفق</string>
<string key="Successful import">واردات موفق</string>
<string key="Highlight name">نام نماد</string>
<string key="Use highlighting">استفاده از برجسته سازی</string>
<string key="Use remote storage">استفاده از ذخیره سازی از راه دور</string>
<string key="Copy bookmarks, highlights and notes to the clipboard">بوک مارک کپی، برجسته و یادداشت ها به کلیپ بورد</string>
<string key="Import bookmarks, highlights and notes from the clipboard">بوک مارک واردات، برجسته و یادداشت ها را از کلیپ بورد</string>
<string key="Highlight">نماد</string>
</translations>
