<?xml version="1.0" encoding="UTF-8"?>
<translations isolang="gl" isolocale="" version="1.0">
<string key="Accent color">Cor Accent</string>
<string key="Add a note">Engadir unha nota</string>
<string key="Add new window">Engadir nova ventá</string>
<string key="Add to bookmarks">Engadir aos favoritos</string>
<string key="Added notes">Engadida notas</string>
<string key="All words (maximum 3 words)">Todas as palabras (máximo 3 palabras)</string>
<string key="An error occurred trying to connect to the network. Try again later.">Houbo un erro ao tentar conectarse á rede. Ténteo de novo máis tarde.</string>
<string key="Autumn">Outono</string>
<string key="Bible">Biblia</string>
<string key="Black and white dark">Escuro branco e negro</string>
<string key="Black and white light">Luz branco e negro</string>
<string key="Blue">Azul</string>
<string key="Bookmarks">Marcadores</string>
<string key="Border color">Cor do borde</string>
<string key="Calvery 2 dark">Calvery 2 escuro</string>
<string key="Calvery 2 light">Calvery 2 Luz</string>
<string key="Calvery dark">Calvery escuro</string>
<string key="Case insensitive">No caso de insensible</string>
<string key="Clear history">Limpar o historial</string>
<string key="Commentaries">Comentarios</string>
<string key="Copy">Copia</string>
<string key="Custom bible download addresses">Enderezos de descarga personalizado Biblia</string>
<string key="Daily plan">Plan diario</string>
<string key="Dark buttons">Botóns escuro</string>
<string key="Day">Día</string>
<string key="Days">Días</string>
<string key="Default settings">A configuración por defecto</string>
<string key="Default system language">Idioma por defecto do sistema</string>
<string key="Delete">Borrar</string>
<string key="Delete?">Borrar?</string>
<string key="Dolphins light">Golfiños luz</string>
<string key="Dolphins">Golfiños</string>
<string key="Download bible list">Descargar lista da Biblia</string>
<string key="Download bible">Descargar Biblia</string>
<string key="Download bibles">Baixo biblias</string>
<string key="Download type">Tipo de descarga</string>
<string key="Download">Descargar</string>
<string key="Edit the theme">Edite o tema</string>
<string key="Edit">Editar</string>
<string key="Exact match">A correspondencia exacta</string>
<string key="Flowers light">Flores luz</string>
<string key="Font">Orixe</string>
<string key="Forest dark">Bosque escuro</string>
<string key="Forest light">Luz Bosque</string>
<string key="Found">Atopado</string>
<string key="From the beginning to the end">Desde o inicio ata o final</string>
<string key="From the camera">A partir da cámara</string>
<string key="From the downloads">Desde os de descargas</string>
<string key="Greek dictionary internet link">Dicionario grego ligazón de internet</string>
<string key="Green">Verde</string>
<string key="Hebrew dictionary internet link">Ligazón de internet hebreo dicionario</string>
<string key="Help">Axudar</string>
<string key="Highlight text markings">Destaque reservas de texto</string>
<string key="History">Historia</string>
<string key="Main background color">Cor de fondo principal</string>
<string key="Main background image">Imaxe de fondo principal</string>
<string key="Main font color">Cor da fonte principal</string>
<string key="Minutes/Day">Minutos por día</string>
<string key="Morphology-Abbreviated form">Forma abreviada</string>
<string key="Morphology-Accusative">Acusativo</string>
<string key="Morphology-Active">Activo</string>
<string key="Morphology-Adjective">Adxectivo</string>
<string key="Morphology-Adverb or adverb and particle combined">Adverbio ou adverbio e partículas combinados</string>
<string key="Morphology-Aeolic">Aeolic</string>
<string key="Morphology-Aorist">Aoristo</string>
<string key="Morphology-Apocopated form">Forma Apocopated</string>
<string key="Morphology-Aramaic transliterated word (indeclinable)">Palabra aramaica transliterado (indeclinável)</string>
<string key="Morphology-Attic Greek form">Forma grega Attic</string>
<string key="Morphology-Attic">Faiado</string>
<string key="Morphology-Comparative">Comparativo</string>
<string key="Morphology-Conditional particle or conjunction">Partícula condicional ou conxunción</string>
<string key="Morphology-Conjunction or conjunctive particle">Conxunción ou partícula conjuntiva</string>
<string key="Morphology-Contracted form">Forma enlazada</string>
<string key="Morphology-Contracted form, or two words merged by crasis">Forma enlazada, ou dúas palabras incorporadas por crase</string>
<string key="Morphology-Correlative or interrogative pronoun">Pronome interrogativo ou correlato</string>
<string key="Morphology-Correlative pronoun">Pronome correlativo</string>
<string key="Morphology-Dative">Dativo</string>
<string key="Morphology-Definite article">Artigo definido</string>
<string key="Morphology-Demonstrative pronoun">Pronome demostrativo</string>
<string key="Morphology-Either middle or passive">De calquera medio ou pasiva</string>
<string key="Morphology-Feminine">Feminino</string>
<string key="Morphology-First person">Primeira persoa</string>
<string key="Morphology-Future">Futuro</string>
<string key="Morphology-Genitive">Genitivo</string>
<string key="Morphology-Hebrew transliterated word (indeclinable)">Palabra hebraica Transliterated (indeclinável)</string>
<string key="Morphology-Imperative">Imperativo</string>
<string key="Morphology-Imperative-sense participle">Imperativo de sentido participio</string>
<string key="Morphology-Imperfect">Imperfecto</string>
<string key="Morphology-Impersonal active">Impersoal activo</string>
<string key="Morphology-Indeclinable Letter (Noun)">Carta indeclinável (substantivo)</string>
<string key="Morphology-Indeclinable Noun of Other type">Substantivo indeclinável de Outro tipo</string>
<string key="Morphology-Indeclinable Numeral (Adjective)">Indeclinável numeral (adxectivo)</string>
<string key="Morphology-Indeclinable Proper Noun">Indeclinável adecuada Substantivo</string>
<string key="Morphology-Indefinite pronoun">Pronome indefinido</string>
<string key="Morphology-Indicative">Indicativo</string>
<string key="Morphology-Infinitive">Infinitivo</string>
<string key="Morphology-Interjection">Interjeição</string>
<string key="Morphology-Interrogative pronoun">Pronome interrogativo</string>
<string key="Morphology-Interrogative">Interrogativo</string>
<string key="Morphology-Irregular or Impure form">Forma irregular ou Impure</string>
<string key="Morphology-Masculine">Feminino</string>
<string key="Morphology-Middle Deponent">Depoente Medio</string>
<string key="Morphology-Middle or passive deponent">Depoente Medio ou pasiva</string>
<string key="Morphology-Middle significance">Significado Medio</string>
<string key="Morphology-Middle">Medio</string>
<string key="Morphology-Negative">Negativo</string>
<string key="Morphology-Neuter">Neutro</string>
<string key="Morphology-No tense stated (adverbial imperative)">O tenso afirmou (imperativo adverbial)</string>
<string key="Morphology-No voice stated">Ningunha voz afirmou</string>
<string key="Morphology-Nominative">Nominativo</string>
<string key="Morphology-Noun">Substantivo</string>
<string key="Morphology-Optative">Optativo</string>
<string key="Morphology-Participle">Participio</string>
<string key="Morphology-Particle attached (with relative pronoun)">Particle fixadas (con pronome relativo)</string>
<string key="Morphology-Particle, disjunctive particle">Particle, partícula disxuntiva</string>
<string key="Morphology-Passive deponent">Depoente pasiva</string>
<string key="Morphology-Passive">Pasiva</string>
<string key="Morphology-Perfect">Perfecto</string>
<string key="Morphology-Personal pronoun">Pronome persoal</string>
<string key="Morphology-Pluperfect">Máis-que-perfecto</string>
<string key="Morphology-Plural">Plural</string>
<string key="Morphology-Possessive pronoun">Pronome posesivo</string>
<string key="Morphology-Preposition">Preposición</string>
<string key="Morphology-Present">Presente</string>
<string key="Morphology-Reciprocal pronoun">Pronome recíproco</string>
<string key="Morphology-Reflexive pronoun">Pronome reflexivo</string>
<string key="Morphology-Relative pronoun">Pronome relativo</string>
<string key="Morphology-Second Aorist">Segundo aoristo</string>
<string key="Morphology-Second Future">Segundo Futuro</string>
<string key="Morphology-Second perfect">En segundo lugar perfecto</string>
<string key="Morphology-Second person">Segunda persoa</string>
<string key="Morphology-Second pluperfect">En segundo lugar máis que perfecto</string>
<string key="Morphology-Singular">Singular</string>
<string key="Morphology-Subjunctive">Subjuntivo</string>
<string key="Morphology-Superlative">Superlativo</string>
<string key="Morphology-Third person">Terceira persoa</string>
<string key="Morphology-Transitive">Transitivo</string>
<string key="Morphology-Verb">Verbo</string>
<string key="Morphology-Vocative">Vocativo</string>
<string key="Name">Nome</string>
<string key="New">Novo</string>
<string key="Next">Seguinte</string>
<string key="Notes">Notas</string>
<string key="Nothing found">Non se atopou nada</string>
<string key="Number of screens">Número de pantallas</string>
<string key="Ocean wave light">Luz da onda de océano</string>
<string key="Ocean wave">Onda de océano</string>
<string key="One or more words">Un ou máis palabras</string>
<string key="Phone default theme">Teléfono tema por defecto</string>
<string key="Pink">Rosa</string>
<string key="Previous">Anterior</string>
<string key="Rate this program">Valorar este programa</string>
<string key="Red">Vermello</string>
<string key="Save">Gardar</string>
<string key="Search conditions">Condicións de investigación</string>
<string key="Search where">Procurar aquí</string>
<string key="Search">Buscar</string>
<string key="Select all">Seleccionar todos</string>
<string key="Select an image">Seleccione unha imaxe</string>
<string key="Select bible to delete">Seleccione biblia para borrar</string>
<string key="Select book and chapter">Seleccione libro e capítulo</string>
<string key="Select book">Seleccione libro</string>
<string key="Select bookmark to delete">Seleccione marcador para borrar</string>
<string key="Select chapter">Seleccione o capítulo</string>
<string key="Select day">Select día</string>
<string key="Select the bible">Seleccione a Biblia</string>
<string key="Select the daily plan start date">Seleccione o plan de data de inicio diaria</string>
<string key="Select the daily plan">Seleccione o plan diario</string>
<string key="Select the language">Seleccione Idioma</string>
<string key="Select the server">Seleccione o servidor</string>
<string key="Select the theme">Seleccione o tema</string>
<string key="Select the window type">Seleccione o tipo de xanela</string>
<string key="Select what you want to hear">Escolla o que quere escoitar</string>
<string key="Send mail">Enviar correo electrónico</string>
<string key="Send message">Enviar mensaxe</string>
<string key="Settings">Configuración</string>
<string key="Share this theme">Compartir este tema</string>
<string key="Show Strong's numbers">Amosar números de Strong</string>
<string key="Show added notes by chapter">Amosar engadir notas por capítulo</string>
<string key="Show note positions">Posicións Amosar nota</string>
<string key="Show the book name on each verse">Amosar o nome do libro en cada verso</string>
<string key="Show the chapter number on each verse">Mostrar o número do capítulo en cada verso</string>
<string key="Show the headings">Amosar as cabeceiras</string>
<string key="Show the verse number on each verse">Amosar o número do versículo en cada verso</string>
<string key="Show the words of Jesus in red">Amosar as palabras de Xesús en vermello</string>
<string key="Show word morphology">Morfoloxía Amosar palabra</string>
<string key="Sky light">Luz Sky</string>
<string key="Start each verse on a new line">Comezar cada verso nunha nova liña</string>
<string key="Swimmer light">Nadador luz</string>
<string key="Swimmer">Nadador</string>
<string key="Talking bible internet link">Falando ligazón de internet Biblia</string>
<string key="Text size">Tamaño do texto</string>
<string key="The New Testement">The New Testement</string>
<string key="The New Testement, Psalms, Proverbs">The New Testement, Salmos, Proverbios</string>
<string key="The Old Testement">O Vello Testement</string>
<string key="The Old and New Testement each day">O Vello eo Novo Testement cada día</string>
<string key="The bible by random chapters">A Biblia por capítulos aleatorios</string>
<string key="The bible by topic">A Biblia por asunto</string>
<string key="Themes">Temas</string>
<string key="Title background color">Título cor de fondo</string>
<string key="Title font color">Cor da fonte Título</string>
<string key="Too many found. Search stopped">Moitos atopado. Busca parado</string>
<string key="Translation">Tradución</string>
<string key="Use an image for the background">Use unha imaxe para o fondo</string>
<string key="Use internet dictionaries">Usar dicionarios internet</string>
<string key="Use small verse numbers">Use pequenos números do verso</string>
<string key="Whole bible">Toda a Biblia</string>
<string key="Winter">Inverno</string>
<string key="You must first select a verse">Primeiro, ten que escoller un versículo</string>
<string key="You must have at least one bible">Debe ter polo menos unha Biblia</string>
<string key="Books">Libros</string>
<string key="Fast search">Procura rápida</string>
<string key="Slow search">Buscar lenta</string>
<string key="Select a chapter">Seleccione un capítulo</string>
<string key="Select a verse">Seleccione un versículo</string>
<string key="My comments">Os meus comentarios</string>
<string key="Translate selected text">Traducir texto seleccionado</string>
<string key="Listen to this chapter">Escoita a esta capítulo</string>
<string key="The first time you do a fast search it takes a long time. Afterwards searching is very quick. Do you want to continue?">A primeira vez que fai unha busca rápida que leva un longo tempo. Despois a buscar é moi rápida. Quere continuar?</string>
<string key="The bible, chronological">A Biblia en orde cronolóxica</string>
<string key="The New Testement, chronological">The New Testement en orde cronolóxica</string>
<string key="Show two title rows in each window">Amosar dúas liñas de título en cada xanela</string>
<string key="Invalid key. Try again">Chave non válida. Ténteo de novo</string>
<string key="Enter key">Tecla Intro</string>
<string key="Unsuccessful import">Importación sen éxito</string>
<string key="Successful import">Importación de éxito</string>
<string key="Highlight name">Centrado o nome</string>
<string key="Use highlighting">Use destaque</string>
<string key="Use remote storage">Usar o almacenamento remoto</string>
<string key="Copy bookmarks, highlights and notes to the clipboard">Bookmarks Copiar, esto e notas para o portarretallos</string>
<string key="Import bookmarks, highlights and notes after you paste the clipboard into the box below">Importar marcadores, esto e notas Despois de pegar o portarretallos no cadro de abaixo</string>
<string key="Highlight">Punto alto</string>
<string key="Synchronize to every verse">Sincronizar cada verso</string>
<string key="None">Ningún</string>
<string key="OneDrive backup / restore">OneDrive backup / restore</string>
<string key="Select the items you want to backup / restore. Then hit the button at the bottom">Seleccione os elementos que quere facer backup / restore. Logo presione o botón ao final</string>
<string key="Backup">Backup</string>
<string key="Restore">Restaurar</string>
<string key="Bookmarks and custom notes">Etiquetas e notas individuais</string>
<string key="Window setup">Diálogo de configuración</string>
<string key="Folder on OneDrive">Cartafol en OneDrive</string>
<string key="Doesn't exist in OneDrive. Remove it and try again">Non existe en OneDrive. Elimina-o e ténteo de novo</string>
<string key="There is no backup to restore">Non hai backup para restaurar</string>
<string key="Connect to OneDrive">Póñase-se OneDrive</string>
<string key="Add a line between notes">Engadir unha liña entre as notas</string>
</translations>
